./.gitignore
./LICENSE
./PKG-INFO
./README.md
./human_loop_server.py
./pyproject.toml
human_in_the_loop_mcp-0.1.0.dist-info/METADATA
human_in_the_loop_mcp-0.1.0.dist-info/WHEEL
human_in_the_loop_mcp-0.1.0.dist-info/entry_points.txt
human_in_the_loop_mcp-0.1.0.dist-info/licenses/LICENSE
human_in_the_loop_mcp-0.1.0.dist-info/RECORD
