Metadata-Version: 2.4
Name: human-in-the-loop-mcp
Version: 0.1.0
Summary: Human-In-the-Loop MCP Server - Enable AI assistants to interact with humans through GUI dialogs
Project-URL: Homepage, https://github.com/GongRzhe/Human-In-the-Loop-MCP-Server
Project-URL: Repository, https://github.com/GongRzhe/Human-In-the-Loop-MCP-Server
Project-URL: Issues, https://github.com/GongRzhe/Human-In-the-Loop-MCP-Server/issues
Project-URL: Documentation, https://github.com/GongRzhe/Human-In-the-Loop-MCP-Server#readme
Project-URL: Changelog, https://github.com/GongRzhe/Human-In-the-Loop-MCP-Server/releases
Author-email: GongRzhe <gongrzhe@gmail.com>
License: MIT
License-File: LICENSE
Keywords: ai-assistant,cross-platform,dialog,fastmcp,gui,human-in-the-loop,mcp,model-context-protocol,tkinter,user-interaction
Classifier: Development Status :: 4 - Beta
Classifier: Intended Audience :: Developers
Classifier: Intended Audience :: Science/Research
Classifier: License :: OSI Approved :: MIT License
Classifier: Operating System :: MacOS
Classifier: Operating System :: Microsoft :: Windows
Classifier: Operating System :: OS Independent
Classifier: Operating System :: POSIX :: Linux
Classifier: Programming Language :: Python :: 3
Classifier: Programming Language :: Python :: 3.8
Classifier: Programming Language :: Python :: 3.9
Classifier: Programming Language :: Python :: 3.10
Classifier: Programming Language :: Python :: 3.11
Classifier: Programming Language :: Python :: 3.12
Classifier: Topic :: Scientific/Engineering :: Artificial Intelligence
Classifier: Topic :: Software Development :: Libraries :: Python Modules
Classifier: Topic :: Software Development :: User Interfaces
Requires-Python: >=3.12
Requires-Dist: fastmcp>=0.1.0
Requires-Dist: pydantic>=2.0.0
Provides-Extra: dev
Requires-Dist: black>=23.0.0; extra == 'dev'
Requires-Dist: mypy>=1.0.0; extra == 'dev'
Requires-Dist: pre-commit>=3.0.0; extra == 'dev'
Requires-Dist: pytest-asyncio>=0.20.0; extra == 'dev'
Requires-Dist: pytest>=7.0.0; extra == 'dev'
Requires-Dist: ruff>=0.1.0; extra == 'dev'
Provides-Extra: test
Requires-Dist: pytest-asyncio>=0.20.0; extra == 'test'
Requires-Dist: pytest-cov>=4.0.0; extra == 'test'
Requires-Dist: pytest-mock>=3.10.0; extra == 'test'
Requires-Dist: pytest>=7.0.0; extra == 'test'
